{
  "identifier": "default",
  "description": "Default capabilities",
  "windows": ["main", "overlay"],
  "permissions": [
    "core:default",
    "global-shortcut:default",
    "clipboard-manager:default",
    {
      "identifier": "core:window:allow-show",
      "allow": [{ "window": "overlay" }]
    },
    {
      "identifier": "core:window:allow-hide",
      "allow": [{ "window": "overlay" }]
    },
    {
      "identifier": "core:window:allow-set-ignore-cursor-events",
      "allow": [{ "window": "overlay" }]
    },
    {
      "identifier": "core:window:allow-set-always-on-top",
      "allow": [{ "window": "overlay" }]
    },
    {
      "identifier": "core:window:allow-set-focusable",
      "allow": [{ "window": "overlay" }]
    },
    {
      "identifier": "core:window:allow-set-decorations",
      "allow": [{ "window": "overlay" }]
    }
  ]
}